lxml-stubs/__init__.pyi
lxml-stubs/cssselect.pyi
lxml-stubs/etree.pyi
lxml-stubs/objectify.pyi
lxml-stubs/html/__init__.pyi
lxml-stubs/html/defs.pyi
lxml_stubs-0.4.0.dist-info/LICENSE
lxml_stubs-0.4.0.dist-info/METADATA
lxml_stubs-0.4.0.dist-info/WHEEL
lxml_stubs-0.4.0.dist-info/top_level.txt
lxml_stubs-0.4.0.dist-info/RECORD
