Metadata-Version: 2.1
Name: lxml-stubs
Version: 0.4.0
Summary: Type annotations for the lxml package
Home-page: UNKNOWN
License: UNKNOWN
Platform: UNKNOWN
Classifier: License :: OSI Approved :: Apache Software License
Provides-Extra: test
License-File: LICENSE
